unifi_dns_sync/__init__.py
unifi_dns_sync/__main__.py
unifi_dns_sync/cli.py
unifi_dns_sync/config.py
unifi_dns_sync/dns_manager.py
unifi_dns_sync/sync.py
unifi_dns_sync-1.0.1.dist-info/licenses/LICENSE
unifi_dns_sync-1.0.1.dist-info/METADATA
unifi_dns_sync-1.0.1.dist-info/WHEEL
unifi_dns_sync-1.0.1.dist-info/entry_points.txt
unifi_dns_sync-1.0.1.dist-info/top_level.txt
unifi_dns_sync-1.0.1.dist-info/RECORD
