Metadata-Version: 2.4
Name: unifi-dns-sync
Version: 1.0.1
Summary: Automatically sync DNS A records on Unifi controllers
Home-page: https://github.com/cswitenky/unifi-dns-sync
Author: cswitenky
Maintainer: cswitenky
License: MIT
Project-URL: Homepage, https://github.com/cswitenky/unifi-dns-sync
Project-URL: Repository, https://github.com/cswitenky/unifi-dns-sync.git
Project-URL: Issues, https://github.com/cswitenky/unifi-dns-sync/issues
Keywords: unifi,dns,networking,automation
Classifier: Development Status :: 4 - Beta
Classifier: Intended Audience :: System Administrators
Classifier: License :: OSI Approved :: MIT License
Classifier: Operating System :: OS Independent
Classifier: Programming Language :: Python :: 3
Classifier: Programming Language :: Python :: 3.8
Classifier: Programming Language :: Python :: 3.9
Classifier: Programming Language :: Python :: 3.10
Classifier: Programming Language :: Python :: 3.11
Classifier: Topic :: Internet :: Name Service (DNS)
Classifier: Topic :: System :: Systems Administration
Requires-Python: >=3.8
License-File: LICENSE
Requires-Dist: requests>=2.28.0
Requires-Dist: urllib3>=1.26.0
Dynamic: home-page
Dynamic: license-file
Dynamic: requires-python
